{"IAH": [1]}
{"JFK": [2]}
{"KUL": [1]}
{"LHR": [1]}
{"MUC": [2]}
{"ORD": [3]}
{"AMS": [2]}
{"ATL": [2]}
{"CAN": [2]}
{"CDG": [1]}
{"CGK": [3]}
{"FCO": [1]}
{"IAH": [2]}
{"JFK": [1]}
{"KUL": [2]}
{"LAS": [2]}
{"LHR": [1]}
{"MIA": [1]}
{"ORD": [2]}
{"ATL": [3]}
{"BKK": [1]}
{"CAN": [2]}
{"CDG": [1]}
{"CGK": [2]}
{"DEN": [2]}
{"JFK": [2]}
{"KUL": [4]}
{"LAS": [1]}
{"LHR": [1]}
{"MUC": [1]}
{"ORD": [2]}
{"AMS": [1]}
{"CGK": [1]}
{"DEN": [3]}
{"DFW": [1]}
{"IAH": [1]}
{"JFK": [3]}
{"KUL": [1]}
{"LAS": [1]}
{"LHR": [3]}
{"MAD": [1]}
{"MUC": [2]}
{"ORD": [3]}
{"PVG": [1]}
{"AMS": [1]}
{"BKK": [2]}
{"CAN": [5]}
{"CGK": [2]}
{"CLT": [1]}
{"DEN": [2]}
{"IAH": [2]}
{"JFK": [2]}
{"LAS": [1]}
{"MUC": [2]}
{"PEK": [1]}
{"PVG": [1]}
{"AMS": [2]}
{"ATL": [2]}
