{"CDG": [1]}
{"CGK": [1]}
{"DEN": [3]}
{"DFW": [2]}
{"HND": [1]}
{"IAH": [2]}
{"JFK": [2]}
{"KUL": [3]}
{"LHR": [1]}
{"ATL": [3]}
{"BKK": [1]}
{"CAN": [2]}
{"CDG": [1]}
{"CGK": [1]}
{"DEN": [3]}
{"DFW": [1]}
{"FCO": [1]}
{"IAH": [1]}
{"JFK": [1]}
{"KUL": [3]}
{"LAS": [1]}
{"MUC": [1]}
{"ORD": [2]}
{"ATL": [1]}
{"CAN": [1]}
{"CGK": [1]}
{"LHR": [1]}
{"ATL": [3]}
{"BKK": [1]}
{"CAN": [1]}
{"CDG": [1]}
{"CGK": [1]}
{"CLT": [2]}
{"DEN": [4]}
{"DFW": [1]}
{"IAH": [2]}
{"KUL": [2]}
{"LHR": [1]}
{"MAD": [1]}
{"MUC": [1]}
{"PEK": [1]}
{"ATL": [1]}
{"CAN": [2]}
{"CDG": [1]}
{"CGK": [3]}
{"CLT": [1]}
{"DEN": [1]}
{"FCO": [2]}
{"IAH": [1]}
{"KUL": [4]}
{"LHR": [1]}
{"MUC": [1]}
{"ORD": [2]}
{"PVG": [2]}
{"AMS": [1]}
{"ATL": [2]}
{"CAN": [2]}
{"CDG": [3]}
